naboopay/__init__.py
naboopay/config/__init__.py
naboopay/config/settings_api.py
naboopay/config/settings_webhook.py
naboopay/models/__init__.py
naboopay/models/models.py
naboopay/src/__init__.py
naboopay/src/auth/__init__.py
naboopay/src/auth/auth.py
naboopay/src/client/__init__.py
naboopay/src/client/client.py
naboopay/src/services/__init__.py
naboopay/src/services/account.py
naboopay/src/services/cashout.py
naboopay/src/services/transaction.py
naboopay/src/webhook/__init__.py
naboopay/src/webhook/webhook.py
naboopay/utils/__init__.py
naboopay/utils/errors.py
naboopay/utils/exceptions.py
naboopay/utils/logger.py
naboopay/utils/utils.py
naboopay-1.0.2.dist-info/licenses/LICENSE
naboopay-1.0.2.dist-info/METADATA
naboopay-1.0.2.dist-info/WHEEL
naboopay-1.0.2.dist-info/top_level.txt
naboopay-1.0.2.dist-info/RECORD
